clientity/__init__.py
clientity/logs.py
clientity/core/__init__.py
clientity/core/client.py
clientity/core/endpoint.py
clientity/core/hints.py
clientity/core/adapters/__init__.py
clientity/core/adapters/_aiohttp.py
clientity/core/adapters/_httpx.py
clientity/core/adapters/_requests.py
clientity/core/adapters/base.py
clientity/core/grouping/__init__.py
clientity/core/grouping/base.py
clientity/core/grouping/namespace.py
clientity/core/grouping/resource.py
clientity/core/primitives/__init__.py
clientity/core/primitives/bound.py
clientity/core/primitives/instructions.py
clientity/core/primitives/method.py
clientity/core/primitives/url.py
clientity/core/protocols/__init__.py
clientity/core/protocols/interface.py
clientity/core/protocols/located.py
clientity/core/protocols/models.py
clientity/core/utils/__init__.py
clientity/core/utils/calls.py
clientity/core/utils/data.py
clientity/core/utils/http.py
clientity/core/utils/misc.py
clientity/core/utils/models.py
clientity/core/utils/typers.py
clientity/exc/__init__.py
clientity/exc/base.py
clientity/exc/http.py
clientity/exc/models.py
clientity-0.1.6.dist-info/METADATA
clientity-0.1.6.dist-info/WHEEL
clientity-0.1.6.dist-info/RECORD
