Metadata-Version: 2.4
Name: clientity
Version: 0.1.6
Summary: rapid http clients
Author-email: Joel Yisrael <schizoprada@gmail.com>
Requires-Dist: loguru
Requires-Dist: pydantic
Provides-Extra: dev
Requires-Dist: pytest; extra == 'dev'
Requires-Dist: pytest-asyncio; extra == 'dev'
Provides-Extra: engines
Requires-Dist: aiohttp; extra == 'engines'
Requires-Dist: httpx; extra == 'engines'
Requires-Dist: requests; extra == 'engines'
